Workbook

Sheet Summary
A1: 200 API & Backend Engineering Stations
A2: Companies are fictional and inspired by real industries. Finishing the stations builds the skills, judgement and portfolio needed for backend roles at these levels; it is not the same as years of production experience. Version 3: Spring Boot 4, Java 25, after the industry gap research.
A4: Stage | B4: Stations | C4: New in v3 | D4: Optional | E4: Reviewer view | F4: Share
A5: Foundations (suggested 0-1 years) | B5: =COUNTIF(Stations!$B$2:$B$201,"Foundations") -> 54 | C5: =COUNTIFS(Stations!$B$2:$B$201,"Foundations",Stations!$E$2:$E$201,"Yes") -> 0 | D5: =COUNTIFS(Stations!$B$2:$B$201,"Foundations",Stations!$D$2:$D$201,"Specialisation") -> 0 | E5: =COUNTIFS(Stations!$B$2:$B$201,"Foundations",Stations!$O$2:$O$201,"Yes") -> 9 | F5: =IF($B$8=0,0,B5/$B$8) -> 0.27
A6: Working Systems (suggested 0-2 years) | B6: =COUNTIF(Stations!$B$2:$B$201,"Working Systems") -> 64 | C6: =COUNTIFS(Stations!$B$2:$B$201,"Working Systems",Stations!$E$2:$E$201,"Yes") -> 7 | D6: =COUNTIFS(Stations!$B$2:$B$201,"Working Systems",Stations!$D$2:$D$201,"Specialisation") -> 3 | E6: =COUNTIFS(Stations!$B$2:$B$201,"Working Systems",Stations!$O$2:$O$201,"Yes") -> 32 | F6: =IF($B$8=0,0,B6/$B$8) -> 0.32
A7: Production Scale (suggested 2-3 years) | B7: =COUNTIF(Stations!$B$2:$B$201,"Production Scale") -> 82 | C7: =COUNTIFS(Stations!$B$2:$B$201,"Production Scale",Stations!$E$2:$E$201,"Yes") -> 7 | D7: =COUNTIFS(Stations!$B$2:$B$201,"Production Scale",Stations!$D$2:$D$201,"Specialisation") -> 8 | E7: =COUNTIFS(Stations!$B$2:$B$201,"Production Scale",Stations!$O$2:$O$201,"Yes") -> 82 | F7: =IF($B$8=0,0,B7/$B$8) -> 0.41
A8: Total | B8: =SUM(B5:B7) -> 200 | C8: =SUM(C5:C7) -> 14 | D8: =SUM(D5:D7) -> 11 | E8: =SUM(E5:E7) -> 123 | F8: =IF($B$8=0,0,B8/$B$8) -> 1
A10: Station type | B10: Stations
A11: Database | B11: =COUNTIF(Stations!$M$2:$M$201,"*Database*") -> 109
A12: Security | B12: =COUNTIF(Stations!$M$2:$M$201,"*Security*") -> 48
A13: Concurrency | B13: =COUNTIF(Stations!$M$2:$M$201,"*Concurrency*") -> 30
A14: Messaging | B14: =COUNTIF(Stations!$M$2:$M$201,"*Messaging*") -> 36
A15: Idempotency | B15: =COUNTIF(Stations!$M$2:$M$201,"*Idempotency*") -> 27
A16: Operations | B16: =COUNTIF(Stations!$M$2:$M$201,"*Operations*") -> 34
A18: New stations are shaded green and optional ones blue on the Stations sheet. A station can have several types.

Sheet Stations
A1: ID | B1: Stage | C1: Suggested experience | D1: Track | E1: New in v3 | F1: Title | G1: Industry | H1: Company (fictional) | I1: Real-world problem | J1: The trap to teach | K1: Main endpoints | L1: Concepts taught | M1: Station types | N1: Required tests | O1: Reviewer view | P1: Infrastructure | Q1: Concepts from stations | R1: Capstone milestones
A2: 1 | B2: Foundations | C2: 0-1 years | D2: Core | E2: No | F2: Is the dark store open? | G2: Quick commerce | H2: Basketo | I2: The app shows 'delivering in 10 minutes' even when the customer's dark store is closed for stock-taking. | J2: Returning null or 200 with an empty body for an unknown store instead of 404. | K2: GET /stores/{storeId}/status | L2: @RestController and @GetMapping; @PathVariable; records as JSON; 200 vs 404 with ResponseEntity; Maven project anatomy; first MockMvc test | M2: API only | N2: • HTTP contract tests (valid, invalid, not found) and a test that reproduces the failure before the fix | O2: No | P2: none | Q2: none
A3: 2 | B3: Foundations | C3: 0-1 years | D3: Core | E3: No | F3: Restaurant menu filters | G3: Food delivery | H3: Tiffino | I3: Customers scroll 140 dishes to find veg items under ₹200; the menu API returns everything, unsorted. | J3: Applying limit before sort, so 'cheapest 5' returns 5 random dishes, sorted. | K3: GET /restaurants/{id}/menu?veg&maxPrice&sort&limit | L3: @RequestParam with defaults; List and Map; Stream filter, sorted, limit; Comparator; query parameter validation | M3: API only | N3: • HTTP contract tests (valid, invalid, not found) and a test that reproduces the failure before the fix | O3: No | P3: none | Q3: 1
A4: 3 | B4: Foundations | C4: 0-1 years | D4: Core | E4: No | F4: Product search autocomplete | G4: E-commerce | H4: Kartwala | I4: Typing 'sam' shows nothing until the full word is typed, and every keystroke scans 2 lakh product names. | J4: Scanning every product name with contains() on each keystroke. | K4: GET /suggestions?prefix&limit | L4: TreeMap and prefix ranges; case-insensitive normalisation; top-N by popularity; input length limits | M4: API only | N4: • HTTP contract tests (valid, invalid, not found) and a test that reproduces the failure before the fix | O4: No | P4: none | Q4: 2
A5: 4 | B5: Foundations | C5: 0-1 years | D5: Core | E5: No | F5: Event registration form | G5: Events | H5: SeatSure | I5: Registrations arrive with empty names, 0 tickets and malformed emails, and the organiser exports garbage. | J5: Trusting the client: no validation, so 0 tickets and empty names are saved. | K5: POST /events/{eventId}/registrations GET /events/{eventId}/registrations/{id} | L5: @PostMapping and @RequestBody; request DTO records; Bean Validation; 201 Created with Location; 400 for invalid input | M5: API only | N5: • HTTP contract tests (valid, invalid, not found) and a test that reproduces the failure before the fix | O5: No | P5: none | Q5: 1
A6: 5 | B6: Foundations | C6: 0-1 years | D6: Core | E6: No | F6: Designing REST resources for gym classes | G6: Fitness | H6: FitNest | I6: The class-booking API has verbs in URLs (/bookClass, /cancelBooking) and returns 200 for everything. | J6: Verbs in URLs and 200 for every outcome, so clients cannot tell what happened. | K6: GET /classes?date POST /classes/{id}/bookings DELETE /bookings/{id} GET /members/{id}/bookings | L6: resource naming; nested vs top-level resources; path vs query parameters; 201, 204, 404 and 409 by meaning | M6: API only | N6: • HTTP contract tests (valid, invalid, not found) and a test that reproduces the failure before the fix | O6: No | P6: none | Q6: 4
A7: 6 | B7: Foundations | C7: 0-1 years | D7: Core | E7: No | F7: One error shape for a banking API | G7: Fintech | H7: Tijori | I7: Every endpoint of the beneficiary API fails differently; the app cannot tell 'wrong IFSC' from 'server down'. | J7: Returning exception messages and stack traces, leaking internals to attackers. | K7: POST /beneficiaries GET /beneficiaries/{id} | L7: custom exceptions; @RestControllerAdvice; ProblemDetail (RFC 9457); 400 vs 404 vs 409; never leak stack traces | M7: Security | N7: • HTTP contract tests (valid, invalid, not found) and a test that reproduces the failure before the fix • 401, 403 and one user accessing another user's data; malicious input | O7: Yes | P7: none | Q7: 4
A8: 7 | B8: Foundations | C8: 0-1 years | D8: Core | E8: No | F8: Comment moderation and XSS-safe output | G8: Social | H8: Chaupal | I8: A comment containing a <script> tag ran in every reader's browser; banned words slip through as 'b@d'. | J8: Filtering '<script>' from input instead of encoding output; attackers bypass the filter. | K8: POST /posts/{id}/comments GET /posts/{id}/comments | L8: XSS and output encoding; validate input, encode output; normalising text before matching; length and rate of input | M8: Security | N8: • HTTP contract tests (valid, invalid, not found) and a test that reproduces the failure before the fix • 401, 403 and one user accessing another user's data; malicious input | O8: Yes | P8: none | Q8: 4
A9: 8 | B9: Foundations | C9: 0-1 years | D9: Core | E9: No | F9: Saved delivery addresses | G9: Food delivery | H9: Tiffino | I9: Editing an address on a flaky network creates duplicates; deleting twice shows an error. | J9: Using POST for edits, so a retry on a flaky network creates duplicates. | K9: PUT /customers/{id}/addresses/{label} PATCH /customers/{id}/addresses/{label} DELETE /customers/{id}/addresses/{label} | L9: PUT vs PATCH; DELETE and 204; idempotent methods; 405 with Allow | M9: Idempotency | N9: • HTTP contract tests (valid, invalid, not found) and a test that reproduces the failure before the fix • a replay test: the same request twice gives one effect | O9: No | P9: none | Q9: 6
A10: 9 | B10: Foundations | C10: 0-1 years | D10: Core | E10: No | F10: Wishlist without duplicates | G10: E-commerce | H10: Kartwala | I10: The same phone appears three times in a wishlist because SKUs arrive as 'ph-12', 'PH-12' and ' PH-12 '. | J10: Overriding equals without hashCode, or using a mutable field as the key. | K10: POST /wishlists/{id}/items GET /wishlists/{id} DELETE /wishlists/{id}/items/{sku} | L10: equals and hashCode; HashSet and HashMap; records' value equality; immutable keys | M10: API only | N10: • HTTP contract tests (valid, invalid, not found) and a test that reproduces the failure before the fix | O10: No | P10: none | Q10: 4
A11: 10 | B11: Foundations | C11: 0-1 years | D11: Core | E11: No | F11: Threaded comment replies | G11: Social | H11: Chaupal | I11: Replies are stored flat; the app shows replies above the comments they answer, and deep threads crash it. | J11: Unbounded recursion on deep threads, crashing with StackOverflowError. | K11: GET /posts/{id}/comment-tree?maxDepth | L11: building a tree from a flat list; Map lookups by parent id; recursion and depth limits; ordering siblings | M11: API only | N11: • HTTP contract tests (valid, invalid, not found) and a test that reproduces the failure before the fix | O11: No | P11: none | Q11: 9
A12: 11 | B12: Foundations | C12: 0-1 years | D12: Core | E12: No | F12: Smart parking slot allocation | G12: Smart cities | H12: Parkora | I12: Cars are sent to the far end of a 6-floor parking while nearer slots stay empty; bikes take car slots. | J12: Re-scanning every slot on each entry instead of keeping free slots ordered. | K12: POST /parking/entries POST /parking/exits/{ticketId} | L12: OOP modelling of a real system; PriorityQueue / TreeSet for nearest slot; enums for vehicle and slot types; fee by duration with rounding up | M12: API only | N12: • HTTP contract tests (valid, invalid, not found) and a test that reproduces the failure before the fix | O12: No | P12: none | Q12: 9
A13: 12 | B13: Foundations | C13: 0-1 years | D13: Core | E13: No | F13: Fleet vehicles: abstract classes vs interfaces | G13: Logistics | H13: Dakroute | I13: Trucks, vans and bikes share copy-pasted code; a new 'EV van' type needed changes in nine places. | J13: Deep inheritance trees where one change in the base class breaks every vehicle. | K13: GET /fleet/vehicles/{id}/service-plan | L13: abstract classes vs interfaces; inheritance vs composition; polymorphic methods; when inheritance hurts | M13: API only | N13: • HTTP contract tests (valid, invalid, not found) and a test that reproduces the failure before the fix | O13: No | P13: none | Q13: 9
... A198: 197 | B198: Production Scale | C198: 2-3 years | D198: Core | E198: No | F198: Usage metering for billing | G198: B2B SaaS | H198: Billora | I198: API usage counted from logs is off by 8%, so some customers are overbilled and others get free calls. | J198: Counting from logs, where duplicates and late events skew the bill. | K198: consumer: usage-events GET /customers/{id}/usage?month | L198: high-volume event aggregation; idempotent upserts; late events and windows; metering vs invoicing | M198: Database, Messaging, Idempotency | N198: • HTTP contract tests (valid, invalid, not found) and a test that reproduces the failure before the fix • rollback and constraint tests against a real database • duplicate-delivery, retry and dead-letter tests • a replay test: the same request twice gives one effect | O198: Yes | P198: kafka, postgres | Q198: 145
A199: 198 | B199: Production Scale | C199: 2-3 years | D199: Core | E199: No | F199: Capstone: quick-commerce order flow | G199: Quick commerce | H199: Basketo | I199: Build the order, inventory and payment flow end to end: reservations, payments, events, caching and failure drills. | J199: Building it in one go, with no milestones, failure drills or design records. | K199: order-service, inventory-service, payment-service | L199: reserve, confirm, release; end-to-end design review; failure drills; production readiness checklist | M199: Database, Security, Concurrency, Messaging, Idempotency, Operations | N199: • HTTP contract tests (valid, invalid, not found) and a test that reproduces the failure before the fix • rollback and constraint tests against a real database • 401, 403 and one user accessing another user's data; malicious input • a real concurrency test that proves the invariant holds • duplicate-delivery, retry and dead-letter tests • a replay test: the same request twice gives one effect • operations section: metric, alert, rollback and runbook; a controlled failure drill | O199: Yes | P199: multi-service, kafka, redis, postgres | Q199: 161, 165, 166 | R199: M1 Order API with validation, errors and migrations M2 Inventory reservations: reserve, confirm, release, with concurrency tests M3 Payments with idempotency keys and webhook handling M4 Events with an outbox, idempotent consumers and a dead-letter topic M5 Redis caching, observability, Docker Compose, failure drills and design records
A200: 199 | B200: Production Scale | C200: 2-3 years | D200: Core | E200: No | F200: Capstone: ride-hailing dispatch platform | G200: Ride-hailing | H200: Rydo | I200: Build ride booking end to end: locations, matching, pricing, trip events and what happens when parts fail. | J200: Designing only for the happy path, with no degraded modes. | K200: rider, driver, dispatch, pricing and trip services | L200: location stream to match to trip; degraded modes; capacity planning; design review and failure drills | M200: Database, Security, Concurrency, Messaging, Idempotency, Operations | N200: • HTTP contract tests (valid, invalid, not found) and a test that reproduces the failure before the fix • rollback and constraint tests against a real database • 401, 403 and one user accessing another user's data; malicious input • a real concurrency test that proves the invariant holds • duplicate-delivery, retry and dead-letter tests • a replay test: the same request twice gives one effect • operations section: metric, alert, rollback and runbook; a controlled failure drill | O200: Yes | P200: multi-service, kafka, redis, postgres | Q200: 121, 131, 152 | R200: M1 Rider and driver APIs with authentication M2 Location ingest and nearby search M3 Matching with locks and fencing, then pricing M4 Trip events, surge pricing and the tracking read model M5 Degraded modes, load test, observability and failure drills
A201: 200 | B201: Production Scale | C201: 2-3 years | D201: Core | E201: No | F201: Capstone: payments platform | G201: Payments | H201: Paysetu | I201: Build payments end to end: intents, provider adapters, webhooks, ledger, settlement and reconciliation. | J201: Trusting that totals balance in the demo without testing failures in the middle of a payment. | K201: payment, ledger, settlement and reconciliation services | L201: payment lifecycle end to end; money correctness under failure; audit and compliance view; reconciliation with the bank | M201: Database, Security, Concurrency, Messaging, Idempotency, Operations | N201: • HTTP contract tests (valid, invalid, not found) and a test that reproduces the failure before the fix • rollback and constraint tests against a real database • 401, 403 and one user accessing another user's data; malicious input • a real concurrency test that proves the invariant holds • duplicate-delivery, retry and dead-letter tests • a replay test: the same request twice gives one effect • operations section: metric, alert, rollback and runbook; a controlled failure drill | O201: Yes | P201: multi-service, kafka, postgres | Q201: 132, 192, 193 | R201: M1 Payment intents with idempotency and provider adapters M2 Unknown outcomes: status checks and webhooks M3 Double-entry ledger with reversals M4 Settlement and reconciliation with bank files M5 Audit, encryption at rest, alerts and failure drills

Sheet Changes in v3
A1: Change | B1: Station | C1: Detail
A2: Added | B2: 106 Expose an API to AI agents with MCP | C2: Model Context Protocol servers with Spring AI; tool names, descriptions and JSON schemas; authenticating and rate-limiting agent callers; read-only vs write tools
A3: Added | B3: 079 Document sharing with relationship-based permissions | C3: relationship-based access control (Zanzibar-style); tuples: user, relation, object; inherited access through folders and teams; OpenFGA or SpiceDB vs your own tables
A4: Added | B4: 087 Saving cards with network tokens | C4: RBI card-on-file tokenisation; network tokens vs card numbers; token lifecycle: create, use, expire, delete; keeping card data out of your systems
A5: Added | B5: 112 Subscriptions with UPI AutoPay mandates | C5: mandate states: created, active, paused, revoked; 24-hour pre-debit notification; per-debit limits and re-authentication; retries without double debits
A6: Added | B6: 104 Enterprise integration with Apache Camel | C6: Apache Camel routes and components; file and SFTP polling; error handlers and dead-letter channels; idempotent consumers for files
A7: Added | B7: 115 Tests that catch weak tests | C7: mutation testing with PIT; property-based tests (jqwik); architecture rules with ArchUnit; what coverage does not tell you
A8: Added | B8: 148 Change data capture with Debezium | C8: change data capture from the database log; Debezium outbox event router; initial snapshots and schema changes; duplicates and ordering by key
A9: Added | B9: 154 A tool-calling agent with guardrails | C9: tool calling with Spring AI; least-privilege tools and excessive agency; human approval for write actions; auditing every tool call
A10: Added | B10: 155 An AI gateway for many models | C10: routing between hosted and self-hosted models; token budgets and rate limits per team; response caching and fallbacks; logging without leaking prompts
A11: Added | B11: 141 Cell-based architecture for a SaaS | C11: cells and a thin cell router; shuffle sharding; limiting the blast radius; moving tenants between cells
A12: Added | B12: 159 COBOL-to-Java with characterisation tests | C12: characterisation (golden master) tests; extracting business rules from legacy code; AI-assisted translation with human review; running old and new side by side
... A61: Updated | B61: 020 Bank statement pages | C61: why live data needs cursors (see the keyset station)

Sheet Station standard
A1: README section and rules
A2: Station standard (applies to every one of the 200 stations)
A3: Each station is a standalone Spring Boot 4 project on Java 25 (LTS). Its README.md has these sections, in this order.
A4: The depth scales with the station: a Foundations station is short; a capstone is long.
A5: 1. Business problem — the fictional company, what breaks today, who it hurts. Companies are fictional, inspired by real industries.
A6: 2. Acceptance criteria — Given / When / Then statements that define "done".
A7: 3. Requirements — what the API must do, as rules.
A8: 4. Learning objectives — what the learner will be able to do and explain.
A9: 5. API contract — methods, URLs, request and response bodies, headers, status codes, error bodies, and real request/response examples captured from the running app.
A10: 6. Edge cases and failure cases — invalid input, missing resources, duplicates, unauthorised access, timeouts, races, unavailable dependencies: whichever apply.
A11: 7. The trap — the plausible-but-wrong approach (from the roadmap's `trap` field), shown failing, with a test where code can show it.
A12: 8. Implementation approach — numbered steps before any code.
... A39: - The platform builds skills, judgement and a portfolio for backend roles; it does not claim to equal years of production experience.

Sheet Capstone milestones
A1: Capstone | B1: Milestone
A2: 198 Capstone: quick-commerce order flow | B2: M1 Order API with validation, errors and migrations
A3: 198 Capstone: quick-commerce order flow | B3: M2 Inventory reservations: reserve, confirm, release, with concurrency tests
A4: 198 Capstone: quick-commerce order flow | B4: M3 Payments with idempotency keys and webhook handling
A5: 198 Capstone: quick-commerce order flow | B5: M4 Events with an outbox, idempotent consumers and a dead-letter topic
A6: 198 Capstone: quick-commerce order flow | B6: M5 Redis caching, observability, Docker Compose, failure drills and design records
A7: 199 Capstone: ride-hailing dispatch platform | B7: M1 Rider and driver APIs with authentication
A8: 199 Capstone: ride-hailing dispatch platform | B8: M2 Location ingest and nearby search
A9: 199 Capstone: ride-hailing dispatch platform | B9: M3 Matching with locks and fencing, then pricing
A10: 199 Capstone: ride-hailing dispatch platform | B10: M4 Trip events, surge pricing and the tracking read model
A11: 199 Capstone: ride-hailing dispatch platform | B11: M5 Degraded modes, load test, observability and failure drills
A12: 200 Capstone: payments platform | B12: M1 Payment intents with idempotency and provider adapters
... A16: 200 Capstone: payments platform | B16: M5 Audit, encryption at rest, alerts and failure drills
